[{"__symbolic":"module","version":3,"metadata":{"SkyListsResourcesProvider":{"__symbolic":"class","decorators":[{"__symbolic":"call","expression":{"__symbolic":"reference","module":"@angular/core","name":"Injectable"}}],"members":{"getString":[{"__symbolic":"method"}]}}}},{"__symbolic":"module","version":1,"metadata":{"SkyListsResourcesProvider":{"__symbolic":"class","decorators":[{"__symbolic":"call","expression":{"__symbolic":"reference","module":"@angular/core","name":"Injectable"}}],"members":{"getString":[{"__symbolic":"method"}]}}}}]